{"title":"Introducción al curso","markdown":{"headingText":"Introducción al curso","headingAttr":{"id":"","classes":["unnumbered"],"keyvalue":[]},"containsRefs":false,"markdown":"\n## Objetivo general\n\nEl objetivo del curso es que las personas adscritas a la CGMEFFI desarrollen habilidades en el uso del software especializado \"R\" para fortalecer el análisis y potenciar el alcance de la información derivada del monitoreo de la política de desarrollo social.\n\n## Temas\n\n**1. Manejo y procesamiento de datos**\n\n1.1 Tipos y estructuras de datos\n\n1.2 Operaciones básicas\n\n1.3 Manejo de datos\n\n1.4 Ciclos, secuencias y condicionales\n\n1.5 Funciones\n\n**2. Visualización de datos**\n\n2.1 Generación de gráficas con ggplot\n\n2.2 Edición de gráficas con ggplot\n\n2.3 Visualización espacial\n\n2.4 Creación de tableros\n\n**3. Análisis de texto**\n\n3.1 Estructura y carga de datos\n\n3.2 Análisis de palabras\n\n3.3 Relación de texto\n\n## Metodología\n\nLa metodología del curso consistirá en lo siguiente:\n\n*1. La exposición de la facilitadora*. Durante la primera parte de la sesión, se expondrán los comandos necesarios para llevar a cabo cada tema. Se dará una introducción sobre la temática y se buscará dar ejemplos concretos para facilitar el aprendizaje. Se espera que el personal exponga sus dudas o comentarios a lo largo de la explicación.\n\n*2. Realización de ejercicios prácticos*. Al final de cada sesión, corresponderá a las personas asistentes del curso realizar individualmente o en parejas un ejercicio relacionado con lo visto en la primera parte de la clase.\n\n*3. Consulta autónoma de material*. Tanto la exposición como los ejercicios serán acompañado de material de consulta realizado ad hoc para el curso y el contenido, de tal manera que el estudiantado pueda volver a los códigos y las explicaciones posteriormente.\n\n## Facilitadoras\n\n### Ana Ruth Escoto Castillo\n\nDoctora en Estudios de Población. Centro de Estudios Demográficos y Urbanos, El Colegio de México.\n\nSemblanza Profesora de tiempo completo en la Facultad de Ciencias Políticas y Sociales. Investigadora nivel I en elSistema Nacional de Investigadores. Maestra en Población y Desarrollo por la Facultad Latinoamericana de Ciencias Sociales (FLACSO) -- Sede México. Posee experiencia en recolección de información estadística, diseño y control de procesos de recolección y su procesamiento. Ha aplicado diversos métodos y herramientas multivariadas, homologación de información y comparabilidad de fuentes en sus investigaciones, así como usa de diversos softwares estadísticos, y ha impartido clases de estadítica aplicada a nivel de licenciatura y posgrado. Es co-coordinadora del Capítulo de CDMX de la iniciativa RLadies.\n\n### Mónica Lara Escalante\n\nDoctora en Ciencia Política. Centro de Investigación y Docencia Económicas (CIDE) México.\n\nSemblanza Gerente de Información y Políticas Públicas en Sertech MX, asistente de docencia en FLACSO México y profesora de asignatura de Estadística en la UNAM. Maestra en Gobierno y Asuntos Públicos por la Facultad Latinoamericana de Ciencias Sociales (FLACSO) -- Sede México. También se ha desempeñado como Analista de Datos Senior en ThinkData MX; como profesora de asignatura y adjunta de diversos cursos de métodos cuantitativos para el análisis de políticas públicas en la Universidad Autónoma de San Luis Potosí, FLACSO México, Centro de Investigación y Docencia Económicas (CIDE) y Universidad Nacional Autónoma de México (UNAM). Sus líneas de investigación son los estudios legislativos, análisis de políticas públicas a nivel local, instituciones y partidos políticos en América Latina.\n"},"formats":{"html":{"execute":{"fig-width":7,"fig-height":5,"fig-format":"retina","fig-dpi":96,"df-print":"default","error":false,"eval":true,"cache":null,"freeze":false,"echo":true,"output":true,"warning":true,"include":true,"keep-md":false,"keep-ipynb":false,"ipynb":null,"enabled":null,"daemon":null,"daemon-restart":false,"debug":false,"ipynb-filters":[],"engine":"markdown"},"render":{"keep-tex":false,"keep-yaml":false,"keep-source":false,"keep-hidden":false,"prefer-html":false,"output-divs":true,"output-ext":"html","fig-align":"default","fig-pos":null,"fig-env":null,"code-fold":"none","code-overflow":"scroll","code-link":false,"code-line-numbers":false,"code-tools":false,"tbl-colwidths":"auto","merge-includes":true,"latex-auto-mk":true,"latex-auto-install":true,"latex-clean":true,"latex-max-runs":10,"latex-makeindex":"makeindex","latex-makeindex-opts":[],"latex-tlmgr-opts":[],"latex-input-paths":[],"latex-output-dir":null,"link-external-icon":false,"link-external-newwindow":false,"self-contained-math":false,"format-resources":[]},"pandoc":{"standalone":true,"wrap":"none","default-image-extension":"png","to":"html","output-file":"index.html"},"language":{},"metadata":{"lang":"en","fig-responsive":true,"quarto-version":"1.1.163","editor":"visual","theme":"spacelab"},"extensions":{"book":{"multiFile":true}}},"pdf":{"execute":{"fig-width":5.5,"fig-height":3.5,"fig-format":"pdf","fig-dpi":300,"df-print":"default","error":false,"eval":true,"cache":null,"freeze":false,"echo":true,"output":true,"warning":true,"include":true,"keep-md":false,"keep-ipynb":false,"ipynb":null,"enabled":null,"daemon":null,"daemon-restart":false,"debug":false,"ipynb-filters":[],"engine":"markdown"},"render":{"keep-tex":false,"keep-yaml":false,"keep-source":false,"keep-hidden":false,"prefer-html":false,"output-divs":true,"output-ext":"pdf","fig-align":"default","fig-pos":null,"fig-env":null,"code-fold":"none","code-overflow":"scroll","code-link":false,"code-line-numbers":false,"code-tools":false,"tbl-colwidths":true,"merge-includes":true,"latex-auto-mk":true,"latex-auto-install":true,"latex-clean":true,"latex-max-runs":10,"latex-makeindex":"makeindex","latex-makeindex-opts":[],"latex-tlmgr-opts":[],"latex-input-paths":[],"latex-output-dir":null,"link-external-icon":false,"link-external-newwindow":false,"self-contained-math":false,"format-resources":[]},"pandoc":{"pdf-engine":"xelatex","standalone":true,"variables":{"graphics":true,"tables":true},"default-image-extension":"pdf","to":"pdf","output-file":"index.pdf"},"language":{},"metadata":{"block-headings":true,"editor":"visual","documentclass":"report"},"extensions":{"book":{}}}}}